{
  "items": [
    {
      "id": 1,
      "title": "Aldor Corporate Video",
      "slug": "video-corporativo-aldor",
      "image": "/images/portfolio/Video-corporativo-Aldor.png",
      "client": "Aldor",
      "category": "Corporate video",
      "video": "c4r5797l0R0"
    },
    {
      "id": 2,
      "title": "FarmGo Lanzamiento Colombia – Yara",
      "slug": "farmgo-lanzamiento-colombia-yara",
      "image": "/images/portfolio/FarmGo-lazanamiento-colombia-Yara.png",
      "client": "Yara",
      "category": "Motion Reel",
      "video": "BS0aeX7ZkRQ"
    },
    {
      "id": 3,
      "title": "Motion Reel - Viernes Studio",
      "slug": "motion-reel-viernes-studio",
      "image": "/images/portfolio/Motion-Reel-Viernes-Studio.png",
      "client": "Aromasynt",
      "category": "Motion Reel",
      "video": "XwwgenbFvEk"
    },
    {
      "id": 4,
      "title": "Apertura Evento Operaciones – Ara",
      "slug": "apertura-evento-operacionaes-ara",
      "image": "/images/portfolio/Apertura-Evento-Operaciones-Ara.png",
      "client": "Ara",
      "category": "Promotional Video",
      "video": "VqP9I22csbE"
    },
    {
      "id": 5,
      "title": "Pimenton - Seminis",
      "slug": "testimonial-pimenton-seminis",
      "image": "/images/portfolio/Testimonial-Pimenton-Seminis.png",
      "client": "Carval",
      "category": "Testimonial Video",
      "video": "IRO-qqb7sw8"
    },
    {
      "id": 6,
      "title": "Viernes Studio",
      "slug": "promotional-video-viernes",
      "image": "/images/portfolio/Video-Promocional-Viernes-Studio.png",
      "client": "Viernes Studio",
      "category": "Promotional Video",
      "video": "7QoG9D-Keqo"
    },
    {
      "id": 7,
      "title": "Aveva – Schneider Electric",
      "slug": "aveva-schneider-electric",
      "image": "/images/portfolio/Aveva-Schneider-electric.png",
      "client": "Schneider Electric",
      "category": "Promotional Video",
      "video": "vadYT_3bBPQ"
    },
    {
      "id": 8,
      "title": "Reels agenda y morrales",
      "slug": "reels-agenda-y-morrales",
      "image": "/images/portfolio/Reels-agenda-y-morrales-Kiutpng.png",
      "client": "Kiut",
      "category": "Promotional Video",
      "video": "rFZbxPxL8vk"
    },
    {
      "id": 9,
      "title": "YaraVita Colombia",
      "slug": "yaravita-colombia",
      "image": "/images/portfolio/YaraVita-Colombia-Yara.png",
      "client": "Yara",
      "category": "Promotional Video",
      "video": "v7w6LCFXIU8"
    },
    {
      "id": 10,
      "title": "Reel Live Action & Motion Design",
      "slug": "reel-ive-action-motion-design",
      "image": "/images/portfolio/Reel-Live-Action-Motion-Design-Viernes-Studio.png",
      "client": "Viernes Studio",
      "category": "Motion Reel",
      "video": "qz9BFfyz6dE"
    },
    {
      "id": 11,
      "title": "Ciencias Agropecuarias",
      "slug": "ciencias-agropecuarias-unal",
      "image": "/images/portfolio/Ciencias-Agropecuarias-UNAL.png",
      "client": "UNAL",
      "category": "Promotional Video",
      "video": "jd9moHNWjyc"
    },
    {
      "id": 12,
      "title": "Sika Ecommerce – Sika",
      "slug": "sika-ecommerce–sika",
      "image": "/images/portfolio/Sika-Ecommerce-Sika.png",
      "client": "Sika",
      "category": "Promotional Video",
      "video": "9S1iAfffcEA"
    },
    {
      "id": 13,
      "title": "Vibrance Expectativa Syngenta",
      "slug": "vibrance-expectativa-syngenta",
      "image": "/images/portfolio/Vibrance-Expectativa-Syngenta.png",
      "client": "Syngenta Colombia",
      "category": "Promotional Video",
      "video": "_2aWCzXMWaQ"
    },
    {
      "id": 14,
      "title": "Tuvimos una idea YCP2017 – Yara",
      "slug": "tuvimos-una-idea-ycp2017-yara",
      "image": "/images/portfolio/Tuvimos-una-idea-YCP2017-Yara.png",
      "client": "Yara",
      "category": "Promotional Video",
      "video": "QdYoN699Lv8"
    },
    {
      "id": 15,
      "title": "Video Promocional – Olivettos",
      "slug": "video-promocional-olivettos",
      "image": "/images/portfolio/Video-Promocional-Olivettos.png",
      "client": "Olivettos",
      "category": "Promotional Video",
      "video": "AqyK3XSJOAQ"
    },
    {
      "id": 16,
      "title": "Campaña Sostenibilidad RRSS – Sika",
      "slug": "campana-sostenibilidad-rrss-sika",
      "image": "/images/portfolio/campana-sostenibilidad-rrss-Sika.png",
      "client": "Sika",
      "category": "Promotional Video",
      "video": "0mRRrNigFss"
    },
    {
      "id": 17,
      "title": "Reels regreso a clases – Kiut",
      "slug": "reels-regreso-a-clases-kiut/",
      "image": "/images/portfolio/Reels-regreso-a-clases-Kiut.png",
      "client": "Kiut",
      "category": "Motion Reel",
      "video": "yn1WGZTgVg8"
    },
    {
      "id": 18,
      "title": "Equipo Claro Coldeportes",
      "slug": "equipo-claro-coldeportes",
      "image": "/images/portfolio/claro-coldeportes.jpg",
      "client": "Claro Colombia",
      "category": "Promotional Video",
      "video": "n7P7TRkUGDc"
    },
    {
      "id": 19,
      "title": "Nuestro Café – Yara",
      "slug": "nuestro-cafe-yara",
      "image": "/images/portfolio/Nuestro-Cafe-Yara.png",
      "client": "Yara",
      "category": "Promotional Video",
      "video": "x-iwfSQCCqo"
    },
    {
      "id": 20,
      "title": "Video Lanzamiento Temporada A 2024 – Kiut",
      "slug": "video-lanzamiento-temporada-a-2024-kiut",
      "image": "/images/portfolio/Video-Lanzamiento-Temporada-A-2024-Kiut.png",
      "client": "Kiut",
      "category": "Corporate video",
      "video": "nsifxNdBRVg"
    },
    {
      "id": 21,
      "title": "DHL Obsequios",
      "slug": "dhl-obsequios",
      "image": "/images/portfolio/Obsequios-DHL.png",
      "client": "DHL",
      "category": "Motion Reel",
      "video": "i8dnj0sRPL0"
    },
    {
      "id": 22,
      "title": "North America Day In The Life – Yara",
      "slug": "north-america-day-in-the-life-yara",
      "image": "/images/portfolio/North-America-Day-In-The-Life-Yara.png",
      "client": "Marketing News",
      "category": "Motion Reel",
      "video": "pTbVhArbt4w"
    },
    {
      "id": 24,
      "title": "Mastercop - Adama",
      "slug": "matercop-adama",
      "image": "/images/portfolio/Mastercop-Adama.png",
      "client": "Adama",
      "category": "Explainer Video",
      "video": "j6BI_kcJT-4"
    },
    {
      "id": 25,
      "title": "Barranqueros Travel – Paintball Combat Zone",
      "slug": "barranqueros-travel-paintball-combat-zone",
      "image": "/images/portfolio/barranqueros.png",
      "client": "Barranqueros Travel",
      "category": "Promotional Video",
      "video": "NzddlIMWQqs"
    },
    {
      "id": 26,
      "title": "Nutrición del ciclista – Zenú",
      "slug": "nutricion-del-ciclista-zenu",
      "image": "/images/portfolio/Nutricion-del-ciclista-Zenu.png",
      "client": "Zenú",
      "category": "Promotional Video",
      "video": "ha1-SWv9LyM"
    },
    {
      "id": 27,
      "title": "Colinagro Institucional",
      "slug": "colinagro-institucional",
      "image": "/images/portfolio/Video-Institucional-Colinagro.png",
      "client": "Colinagro",
      "category": "Corporate video",
      "video": "1OoT1v848fw"
    },
    {
      "id": 29,
      "title": "Aquaoccidente potabilización",
      "slug": "aquaoccidente-potabilizacion",
      "image": "/images/portfolio/Video-Comercial-2022-Aquaoccidente.png",
      "client": "Aquaoccidente",
      "category": "Comercial Video",
      "video": "FHxHI3_-9O4"
    },
    {
      "id": 30,
      "title": "Promocional Blue Fox",
      "slug": "promocional-blue-fox",
      "image": "/images/portfolio/bluefox.jpg",
      "client": "Blue Fox",
      "category": "Promotional Video",
      "video": "0lYPqAZTlXU"
    }
  ]
}
